pyfii/__init__.py
pyfii/drone.py
pyfii/fii.py
pyfii/read.py
pyfii/show.py
pyfii/cv3d/IIID.py
pyfii/cv3d/IIID2.py
pyfii/cv3d/__init__.py
pyfii/cv3d/transfer.py
pyfii-1.3.0.dist-info/LICENSE
pyfii-1.3.0.dist-info/METADATA
pyfii-1.3.0.dist-info/WHEEL
pyfii-1.3.0.dist-info/top_level.txt
pyfii-1.3.0.dist-info/RECORD
