Metadata-Version: 2.1
Name: pyfii
Version: 1.3.0
Summary: 这个库可以让我们用python写Fii的无人机程序，有三视图模拟飞行的功能，模拟飞行更方便观看
Author-email: Kevin0412 <kevin0412_xlt@qq.com>
Project-URL: Homepage, https://github.com/Kevin0412/pyfii
Project-URL: Bug Tracker, https://github.com/Kevin0412/pyfii/issues
Classifier: Programming Language :: Python :: 3
Classifier: License :: OSI Approved :: GNU General Public License v3 (GPLv3)
Classifier: Operating System :: OS Independent
Requires-Python: >=3.7
License-File: LICENSE
